osym/io.py
osym_io-0.1.2.dist-info/METADATA
osym_io-0.1.2.dist-info/WHEEL
osym_io-0.1.2.dist-info/top_level.txt
osym_io-0.1.2.dist-info/RECORD
