Metadata-Version: 2.4
Name: osym.io
Version: 0.1.2
Summary: Objects with SYMbolic expressions - IO
Author-email: nzturn <nzturn@gmail.com>
Keywords: symbolic,dsl
Classifier: Development Status :: 3 - Alpha
Classifier: Intended Audience :: Developers
Classifier: Programming Language :: Python :: 3
Requires-Python: >=3.8
Requires-Dist: osym
